s3cache/__init__.py
s3cache/s3cache.py
s3werkzeugcache-0.2.1.dist-info/LICENSE.txt
s3werkzeugcache-0.2.1.dist-info/METADATA
s3werkzeugcache-0.2.1.dist-info/WHEEL
s3werkzeugcache-0.2.1.dist-info/top_level.txt
s3werkzeugcache-0.2.1.dist-info/RECORD
