Metadata-Version: 2.1
Name: s3werkzeugcache
Version: 0.2.1
Summary: S3 implementation of the werkzeug cache
Home-page: https://github.com/bkyryliuk/s3werkzeugcache
Author: Bogdan Kyryliuk
Author-email: b.kyryliuk@gmail.com
License: UNKNOWN
Download-URL: https://github.com/bogdan-kyryliuk/s3cache/tarball/0.2.1
Platform: UNKNOWN
Classifier: Programming Language :: Python :: 2.7
Classifier: Programming Language :: Python :: 3.4
Classifier: Programming Language :: Python :: 3.5
Classifier: Programming Language :: Python :: 3.6
Requires-Dist: boto3
Requires-Dist: cachelib
